RSPFilter
